gct/__init__.py
gct/__main__.py
gct/api.py
gct/constants.py
gct/network.py
gct/package_config.py
gct/parse.py
gct/syntax_tree.py
gct/type_check.py
gct/url.py
gct/utils.py
gct_py-0.1.6.dist-info/LICENSE
gct_py-0.1.6.dist-info/METADATA
gct_py-0.1.6.dist-info/WHEEL
gct_py-0.1.6.dist-info/top_level.txt
gct_py-0.1.6.dist-info/RECORD
