Metadata-Version: 2.1
Name: gct-py
Version: 0.1.6
Summary: Visualize Python code at lightning speed
Author-email: Qasim Wani <qasim@vt.edu>
Project-URL: Homepage, https://gctpy.com
Project-URL: Bug Tracker, https://github.com/QasimWani/gct/issues
Classifier: Programming Language :: Python :: 3
Classifier: License :: OSI Approved :: GNU General Public License v3 (GPLv3)
Classifier: Operating System :: OS Independent
Requires-Python: >=3.7
License-File: LICENSE
